PyLabEHPY/Lab.py
PyLabEHPY/__init__.py
PyLabEHPY-0.5.1.dist-info/LICENSE.txt
PyLabEHPY-0.5.1.dist-info/METADATA
PyLabEHPY-0.5.1.dist-info/WHEEL
PyLabEHPY-0.5.1.dist-info/top_level.txt
PyLabEHPY-0.5.1.dist-info/RECORD
