Metadata-Version: 2.1
Name: PyLabEHPY
Version: 0.5.1
Summary: Pacote para interagir com o PyLab do EHPY
Home-page: https://github.com/ualvesdias/PyLabEHPY
Download-URL: https://github.com/ualvesdias/PyLabEHPY/archive/refs/tags/0.4.tar.gz
Author: Ulisses Alves
Author-email: ulisses.alves@protonmail.com
License: MIT
Keywords: PyLabEHPY
Classifier: Development Status :: 5 - Production/Stable
Classifier: Intended Audience :: Developers
Classifier: Topic :: Software Development :: Build Tools
Classifier: License :: OSI Approved :: MIT License
Classifier: Programming Language :: Python :: 3.12
License-File: LICENSE.txt
Requires-Dist: requests
